<?xml version="1.0" encoding="utf-8"?><items termsofuse="http://boardgamegeek.com/xmlapi/termsofuse"><item type="boardgameexpansion" id="153748">
         <thumbnail>//cf.geekdo-images.com/images/pic1902264_t.jpg</thumbnail>
      <image>//cf.geekdo-images.com/images/pic1902264.jpg</image>
                                     				
				<name type="primary" sortindex="1" value="Forbidden Desert: Storm Tracker Gear Card" />
			
						                           
						               													<description>An extra gear card for the cooperative game Forbidden Desert. It doesn't come in the standard deck. If drawn it allows the player to &amp;quot;Look at the top storm cards, equal to the Storm level, and place one at the bottom of the deck.&amp;quot; It can be played at any time and does not count as an action.&amp;#10;&amp;#10;</description>
										      	               				<yearpublished value="2013" />
						               				<minplayers value="2" />
						               				<maxplayers value="5" />
						      			<poll name="suggested_numplayers" title="User Suggested Number of Players" totalvotes="1">
			
		<results numplayers="1">		
					<result value="Best" numvotes="0" />
					<result value="Recommended" numvotes="0" />
					<result value="Not Recommended" numvotes="0" />
				</results>					
			
		<results numplayers="2">		
					<result value="Best" numvotes="0" />
					<result value="Recommended" numvotes="1" />
					<result value="Not Recommended" numvotes="0" />
				</results>					
			
		<results numplayers="3">		
					<result value="Best" numvotes="0" />
					<result value="Recommended" numvotes="1" />
					<result value="Not Recommended" numvotes="0" />
				</results>					
			
		<results numplayers="4">		
					<result value="Best" numvotes="0" />
					<result value="Recommended" numvotes="1" />
					<result value="Not Recommended" numvotes="0" />
				</results>					
			
		<results numplayers="5">		
					<result value="Best" numvotes="1" />
					<result value="Recommended" numvotes="0" />
					<result value="Not Recommended" numvotes="0" />
				</results>					
			
		<results numplayers="5+">		
					<result value="Best" numvotes="0" />
					<result value="Recommended" numvotes="0" />
					<result value="Not Recommended" numvotes="0" />
				</results>					
	</poll> 
			               				<playingtime value="45" />
						               				<minplaytime value="45" />
						               				<maxplaytime value="45" />
						               				<minage value="10" />
						      			<poll name="suggested_playerage" title="User Suggested Player Age" totalvotes="1">
			<results>		
					<result value="2" numvotes="0" />
					<result value="3" numvotes="0" />
					<result value="4" numvotes="0" />
					<result value="5" numvotes="0" />
					<result value="6" numvotes="0" />
					<result value="8" numvotes="0" />
					<result value="10" numvotes="1" />
					<result value="12" numvotes="0" />
					<result value="14" numvotes="0" />
					<result value="16" numvotes="0" />
					<result value="18" numvotes="0" />
					<result value="21 and up" numvotes="0" />
				</results>					
	</poll> 
			      			<poll name="language_dependence" title="Language Dependence" totalvotes="1">
			
		<results>		
					<result level="1" value="No necessary in-game text" numvotes="0" />
					<result level="2" value="Some necessary text - easily memorized or small crib sheet" numvotes="1" />
					<result level="3" value="Moderate in-game text - needs crib sheet or paste ups" numvotes="0" />
					<result level="4" value="Extensive use of text - massive conversion needed to be playable" numvotes="0" />
					<result level="5" value="Unplayable in another language" numvotes="0" />
				</results>					
	</poll> 
			      			 
			      				
		 			

			
		
					<link type="boardgamecategory" id="1042" value="Expansion for Base-game" />
		
									
			

			      				
		 			

			
		
					<link type="boardgamemechanic" id="2023" value="Co-operative Play" />
		
									
			

			      				
		 			

			
		
					<link type="boardgamefamily" id="23532" value="Promotional Cards" />
		
									
			

			      			

			      				
		 			

			
		
					<link type="boardgameexpansion" id="136063" value="Forbidden Desert" inbound="true"/>
		
									
			

			      			

			      			

			      			

			      			

			      			

			      	      	      				
		 			

			
		
					<link type="boardgamedesigner" id="378" value="Matt Leacock" />
		
									
			

			      			

			      	      				
		 			

			
		
					<link type="boardgamepublisher" id="108" value="Gamewright" />
		
									
				
		 			

			
		
					<link type="boardgamepublisher" id="17786" value="uplay.it edizioni" />
		
									
			

			
	

	

	
	
	
   		<statistics page="1">
								<ratings >
			<usersrated value="119" />
			<average value="6.76092" />
			<bayesaverage value="5.65481" />

			<ranks>
															<rank type="subtype" id="1" name="boardgame" friendlyname="Board Game Rank" value="Not Ranked" bayesaverage="5.65481" />
												</ranks>

			<stddev value="1.56283" />
			<median value="0" />
			<owned value="625" />
			<trading value="12" />
			<wanting value="38" />
			<wishing value="75" />
			<numcomments value="52" />
			<numweights value="4" />
			<averageweight value="1.75" />
			</ratings>
								</statistics>
     
	
          
</item>
</items>