<?xml version="1.0" encoding="utf-8"?><items termsofuse="http://boardgamegeek.com/xmlapi/termsofuse"><item type="boardgameexpansion" id="22884">
         <thumbnail>//cf.geekdo-images.com/images/pic359643_t.jpg</thumbnail>
      <image>//cf.geekdo-images.com/images/pic359643.jpg</image>
                                     				
				<name type="primary" sortindex="1" value="Lord of the Rings: Battlefields" />
			
						                               				
				<name type="alternate" sortindex="5" value="Der Herr der Ringe: Schlachtfelder" />
			    				
				<name type="alternate" sortindex="4" value="Le Seigneur des Anneaux: Champs de Bataille" />
			
						               													<description>Reiner Knizia gives us a new expansion for the classic Lord of the Rings board game. Each of the boards from the main game has a corresponding battlefield, and players maneuver heroes and villains on these battlefields to improve their position in the fully integrated main game.&amp;#10;&amp;#10;From the ancient ruins of Weathertop to the conflict at the Black Gate of Mordor, the journey of the Fellowship of the Ring is marked with battle. The armies of Sauron are on the march, and unless the courage and faith of the Fellowship can hold, the Shadow will be victorious.&amp;#10;&amp;#10;The new Battlefields expansion for Reiner Knizia's acclaimed Lord of the Rings board game focuses on the deadly combats that the Fellowship must survive on its quest to destroy the One Ring. Now in addition to guiding the Fellowship through its many perils, the players also help to hinder or defeat Sauron's powerful armies, because the farther enemies march on the battlefield board, the more destruction they cause and the closer Sauron comes to recovering the One Ring!&amp;#10;&amp;#10;Will Aragorn arrive in time to defend against the Witch King at Weathertop? Will Boromir's courage hold against the savage Uruk-Hai? Will Gimli's axe be enough to withstand a horde of orcs at the Chamber of Mazarbul? Join the fight with the Lord of the Rings: Battlefields expansion.&amp;#10;&amp;#10;Contents&amp;#10;&amp;#10;    3 double-sided battlefield boards &amp;#10;    5 Fellowship pieces &amp;#10;    30 Enemy pieces &amp;#10;    20 trigger tiles &amp;#10;    6 Feature cards &amp;#10;    3 Gandalf cards &amp;#10;&amp;#10;&amp;#10;&amp;#10;&amp;#10;&amp;#10;Expands:&amp;#10;&amp;#10;    Lord of the Rings&amp;#10;&amp;#10;&amp;#10;&amp;#10;&amp;#10;</description>
										      	               				<yearpublished value="2007" />
						               				<minplayers value="2" />
						               				<maxplayers value="5" />
						      			<poll name="suggested_numplayers" title="User Suggested Number of Players" totalvotes="5">
			
		<results numplayers="1">		
					<result value="Best" numvotes="1" />
					<result value="Recommended" numvotes="1" />
					<result value="Not Recommended" numvotes="1" />
				</results>					
			
		<results numplayers="2">		
					<result value="Best" numvotes="0" />
					<result value="Recommended" numvotes="3" />
					<result value="Not Recommended" numvotes="0" />
				</results>					
			
		<results numplayers="3">		
					<result value="Best" numvotes="2" />
					<result value="Recommended" numvotes="1" />
					<result value="Not Recommended" numvotes="0" />
				</results>					
			
		<results numplayers="4">		
					<result value="Best" numvotes="3" />
					<result value="Recommended" numvotes="1" />
					<result value="Not Recommended" numvotes="0" />
				</results>					
			
		<results numplayers="5">		
					<result value="Best" numvotes="2" />
					<result value="Recommended" numvotes="1" />
					<result value="Not Recommended" numvotes="0" />
				</results>					
			
		<results numplayers="5+">		
					<result value="Best" numvotes="0" />
					<result value="Recommended" numvotes="1" />
					<result value="Not Recommended" numvotes="1" />
				</results>					
	</poll> 
			               				<playingtime value="0" />
						               				<minplaytime value="0" />
						               				<maxplaytime value="0" />
						               				<minage value="12" />
						      			<poll name="suggested_playerage" title="User Suggested Player Age" totalvotes="0">
			<results>		
					<result value="2" numvotes="0" />
					<result value="3" numvotes="0" />
					<result value="4" numvotes="0" />
					<result value="5" numvotes="0" />
					<result value="6" numvotes="0" />
					<result value="8" numvotes="0" />
					<result value="10" numvotes="0" />
					<result value="12" numvotes="0" />
					<result value="14" numvotes="0" />
					<result value="16" numvotes="0" />
					<result value="18" numvotes="0" />
					<result value="21 and up" numvotes="0" />
				</results>					
	</poll> 
			      			<poll name="language_dependence" title="Language Dependence" totalvotes="1">
			
		<results>		
					<result level="6" value="No necessary in-game text" numvotes="0" />
					<result level="7" value="Some necessary text - easily memorized or small crib sheet" numvotes="1" />
					<result level="8" value="Moderate in-game text - needs crib sheet or paste ups" numvotes="0" />
					<result level="9" value="Extensive use of text - massive conversion needed to be playable" numvotes="0" />
					<result level="10" value="Unplayable in another language" numvotes="0" />
				</results>					
	</poll> 
			      			 
			      				
		 			

			
		
					<link type="boardgamecategory" id="1022" value="Adventure" />
		
									
				
		 			

			
		
					<link type="boardgamecategory" id="1042" value="Expansion for Base-game" />
		
									
				
		 			

			
		
					<link type="boardgamecategory" id="1010" value="Fantasy" />
		
									
				
		 			

			
		
					<link type="boardgamecategory" id="1093" value="Novel-based" />
		
									
			

			      				
		 			

			
		
					<link type="boardgamemechanic" id="2023" value="Co-operative Play" />
		
									
				
		 			

			
		
					<link type="boardgamemechanic" id="2072" value="Dice Rolling" />
		
									
				
		 			

			
		
					<link type="boardgamemechanic" id="2040" value="Hand Management" />
		
									
				
		 			

			
		
					<link type="boardgamemechanic" id="2011" value="Modular Board" />
		
									
				
		 			

			
		
					<link type="boardgamemechanic" id="2015" value="Variable Player Powers" />
		
									
			

			      				
		 			

			
		
					<link type="boardgamefamily" id="4684" value="Lord of the Rings (Reiner Knizia's co-op game)" />
		
									
				
		 			

			
		
					<link type="boardgamefamily" id="4263" value="Tolkien Games" />
		
									
			

			      			

			      				
		 			

			
		
					<link type="boardgameexpansion" id="823" value="Lord of the Rings" inbound="true"/>
		
									
			

			      			

			      			

			      			

			      			

			      			

			      	      	      				
		 			

			
		
					<link type="boardgamedesigner" id="2" value="Reiner Knizia" />
		
									
			

			      				
		 			

			
		
					<link type="boardgameartist" id="11884" value="John Howe" />
		
									
				
		 			

			
		
					<link type="boardgameartist" id="11989" value="Brian Schomburg" />
		
									
			

			      	      				
		 			

			
		
					<link type="boardgamepublisher" id="531" value="Esdevium" />
		
									
				
		 			

			
		
					<link type="boardgamepublisher" id="17" value="Fantasy Flight Games" />
		
									
				
		 			

			
		
					<link type="boardgamepublisher" id="264" value="Heidelberger Spieleverlag" />
		
									
				
		 			

			
		
					<link type="boardgamepublisher" id="3446" value="Ubik" />
		
									
			

			
	

	

	
	
	
   		<statistics page="1">
								<ratings >
			<usersrated value="441" />
			<average value="7.15442" />
			<bayesaverage value="6.07737" />

			<ranks>
															<rank type="subtype" id="1" name="boardgame" friendlyname="Board Game Rank" value="Not Ranked" bayesaverage="6.07737" />
																				<rank type="family" id="5496" name="thematic" friendlyname="Thematic Rank" value="Not Ranked" bayesaverage="6.37342" />
											<rank type="family" id="5497" name="strategygames" friendlyname="Strategy Game Rank" value="Not Ranked" bayesaverage="6.20576" />
												</ranks>

			<stddev value="1.36777" />
			<median value="0" />
			<owned value="1601" />
			<trading value="32" />
			<wanting value="179" />
			<wishing value="348" />
			<numcomments value="232" />
			<numweights value="56" />
			<averageweight value="3.0893" />
			</ratings>
								</statistics>
     
	
          
</item>
<item type="boardgameexpansion" id="2449">
         <thumbnail>//cf.geekdo-images.com/images/pic1654876_t.jpg</thumbnail>
      <image>//cf.geekdo-images.com/images/pic1654876.jpg</image>
                                     				
				<name type="primary" sortindex="1" value="Lord of the Rings: Friends &amp; Foes" />
			
						                               				
				<name type="alternate" sortindex="5" value="Der Herr der Ringe: Die Feinde" />
			    				
				<name type="alternate" sortindex="1" value="In de Ban van de Ring: Vrienden en Vijanden" />
			    				
				<name type="alternate" sortindex="4" value="Le Seigneur des Anneaux: Les Forces des Ténèbres" />
			
						               													<description>This expansion to the Lord of the Rings board game adds two new scenario boards (Bree and Isengard), 13 new feature cards and 3 new Gandalf cards. It also adds two completely new features to the game: Foe cards which add a major new aspect to the game; and Character Ability cards which give each character a unique one-shot ability.&amp;#10;&amp;#10;Expanded by&amp;#10;&amp;#10;     The Black Gate / Das Schwarze Tor&amp;#10;         A small 4 card package. Given away free at cons/fairs or gamestores.&amp;#10;         Freely printable from the Reiner Knizia Cool Stuff webpage or the files section below.&amp;#10;    &amp;#10;&amp;#10;&amp;#10;&amp;#10;&amp;#10;</description>
										      	               				<yearpublished value="2001" />
						               				<minplayers value="2" />
						               				<maxplayers value="5" />
						      			<poll name="suggested_numplayers" title="User Suggested Number of Players" totalvotes="20">
			
		<results numplayers="1">		
					<result value="Best" numvotes="1" />
					<result value="Recommended" numvotes="6" />
					<result value="Not Recommended" numvotes="10" />
				</results>					
			
		<results numplayers="2">		
					<result value="Best" numvotes="2" />
					<result value="Recommended" numvotes="14" />
					<result value="Not Recommended" numvotes="3" />
				</results>					
			
		<results numplayers="3">		
					<result value="Best" numvotes="6" />
					<result value="Recommended" numvotes="13" />
					<result value="Not Recommended" numvotes="0" />
				</results>					
			
		<results numplayers="4">		
					<result value="Best" numvotes="14" />
					<result value="Recommended" numvotes="5" />
					<result value="Not Recommended" numvotes="0" />
				</results>					
			
		<results numplayers="5">		
					<result value="Best" numvotes="4" />
					<result value="Recommended" numvotes="11" />
					<result value="Not Recommended" numvotes="4" />
				</results>					
			
		<results numplayers="5+">		
					<result value="Best" numvotes="0" />
					<result value="Recommended" numvotes="2" />
					<result value="Not Recommended" numvotes="13" />
				</results>					
	</poll> 
			               				<playingtime value="90" />
						               				<minplaytime value="90" />
						               				<maxplaytime value="90" />
						               				<minage value="12" />
						      			<poll name="suggested_playerage" title="User Suggested Player Age" totalvotes="6">
			<results>		
					<result value="2" numvotes="0" />
					<result value="3" numvotes="0" />
					<result value="4" numvotes="0" />
					<result value="5" numvotes="0" />
					<result value="6" numvotes="0" />
					<result value="8" numvotes="0" />
					<result value="10" numvotes="2" />
					<result value="12" numvotes="3" />
					<result value="14" numvotes="1" />
					<result value="16" numvotes="0" />
					<result value="18" numvotes="0" />
					<result value="21 and up" numvotes="0" />
				</results>					
	</poll> 
			      			<poll name="language_dependence" title="Language Dependence" totalvotes="11">
			
		<results>		
					<result level="1" value="No necessary in-game text" numvotes="0" />
					<result level="2" value="Some necessary text - easily memorized or small crib sheet" numvotes="1" />
					<result level="3" value="Moderate in-game text - needs crib sheet or paste ups" numvotes="9" />
					<result level="4" value="Extensive use of text - massive conversion needed to be playable" numvotes="1" />
					<result level="5" value="Unplayable in another language" numvotes="0" />
				</results>					
	</poll> 
			      			 
			      				
		 			

			
		
					<link type="boardgamecategory" id="1022" value="Adventure" />
		
									
				
		 			

			
		
					<link type="boardgamecategory" id="1042" value="Expansion for Base-game" />
		
									
				
		 			

			
		
					<link type="boardgamecategory" id="1010" value="Fantasy" />
		
									
				
		 			

			
		
					<link type="boardgamecategory" id="1093" value="Novel-based" />
		
									
			

			      				
		 			

			
		
					<link type="boardgamemechanic" id="2023" value="Co-operative Play" />
		
									
				
		 			

			
		
					<link type="boardgamemechanic" id="2072" value="Dice Rolling" />
		
									
				
		 			

			
		
					<link type="boardgamemechanic" id="2040" value="Hand Management" />
		
									
				
		 			

			
		
					<link type="boardgamemechanic" id="2011" value="Modular Board" />
		
									
				
		 			

			
		
					<link type="boardgamemechanic" id="2015" value="Variable Player Powers" />
		
									
			

			      				
		 			

			
		
					<link type="boardgamefamily" id="4684" value="Lord of the Rings (Reiner Knizia's co-op game)" />
		
									
				
		 			

			
		
					<link type="boardgamefamily" id="4263" value="Tolkien Games" />
		
									
			

			      				
		 			

			
		
					<link type="boardgameexpansion" id="72661" value="Lord of the Rings: The Black Gate" />
		
									
			

			      				
		 			

			
		
					<link type="boardgameexpansion" id="823" value="Lord of the Rings" inbound="true"/>
		
									
			

			      			

			      			

			      			

			      			

			      			

			      	      	      				
		 			

			
		
					<link type="boardgamedesigner" id="2" value="Reiner Knizia" />
		
									
			

			      				
		 			

			
		
					<link type="boardgameartist" id="11884" value="John Howe" />
		
									
			

			      	      				
		 			

			
		
					<link type="boardgamepublisher" id="267" value="999 Games" />
		
									
				
		 			

			
		
					<link type="boardgamepublisher" id="17" value="Fantasy Flight Games" />
		
									
				
		 			

			
		
					<link type="boardgamepublisher" id="51" value="Hasbro" />
		
									
				
		 			

			
		
					<link type="boardgamepublisher" id="37" value="KOSMOS" />
		
									
				
		 			

			
		
					<link type="boardgamepublisher" id="28" value="Parker Brothers" />
		
									
				
		 			

			
		
					<link type="boardgamepublisher" id="36" value="Sophisticated Games" />
		
									
				
		 			

			
		
					<link type="boardgamepublisher" id="42" value="Tilsit" />
		
									
			

			
	

	

	
	
	
   		<statistics page="1">
								<ratings >
			<usersrated value="2458" />
			<average value="7.27814" />
			<bayesaverage value="6.80816" />

			<ranks>
															<rank type="subtype" id="1" name="boardgame" friendlyname="Board Game Rank" value="Not Ranked" bayesaverage="6.80816" />
																				<rank type="family" id="5496" name="thematic" friendlyname="Thematic Rank" value="Not Ranked" bayesaverage="6.98413" />
											<rank type="family" id="5497" name="strategygames" friendlyname="Strategy Game Rank" value="Not Ranked" bayesaverage="6.8906" />
												</ranks>

			<stddev value="1.32068" />
			<median value="0" />
			<owned value="5561" />
			<trading value="226" />
			<wanting value="110" />
			<wishing value="239" />
			<numcomments value="1013" />
			<numweights value="233" />
			<averageweight value="2.7897" />
			</ratings>
								</statistics>
     
	
          
</item>
<item type="boardgameexpansion" id="3819">
         <thumbnail>//cf.geekdo-images.com/images/pic1654883_t.jpg</thumbnail>
      <image>//cf.geekdo-images.com/images/pic1654883.jpg</image>
                                     				
				<name type="primary" sortindex="1" value="Lord of the Rings: Sauron" />
			
						                               				
				<name type="alternate" sortindex="5" value="Der Herr der Ringe: Sauron" />
			    				
				<name type="alternate" sortindex="1" value="In de Ban van de Ring: Sauron" />
			    				
				<name type="alternate" sortindex="4" value="Le Seigneur des Anneaux: Sauron" />
			    				
				<name type="alternate" sortindex="4" value="Il Signore degli Anelli: Sauron" />
			
						               													<description>From back of box:&amp;#10;&amp;#10;Two thousand years have passed since Sauron was defeated by the last alliance of men and elves. Now he has risen again and seeks to recover his one ring, the source of all power.&amp;#10;&amp;#10;In this expansion one player takes the part of Sauron, the Dark Lord, and plays against the fellowship. Sauron watches over the players' every move and uses the Black Rider figure and special Sauron and Nazgul cards to strike. New resources come to the Hobbits' support.&amp;#10;&amp;#10;Once again you are called upon to master this exciting continuation of the great adventure and lead the Fellowship to victory. Alternatively, take command of Sauron's dark forces to catch and eradicate these defiant Hobbits before they can destroy your ring...&amp;#10;&amp;#10;Also included: Dark events, an independent set of event tiles that increases the challenges of the original board game and its expansions. Some event tiles may now be rejected - you decide.&amp;#10;&amp;#10;</description>
										      	               				<yearpublished value="2002" />
						               				<minplayers value="3" />
						               				<maxplayers value="6" />
						      			<poll name="suggested_numplayers" title="User Suggested Number of Players" totalvotes="14">
			
		<results numplayers="1">		
					<result value="Best" numvotes="0" />
					<result value="Recommended" numvotes="2" />
					<result value="Not Recommended" numvotes="7" />
				</results>					
			
		<results numplayers="2">		
					<result value="Best" numvotes="1" />
					<result value="Recommended" numvotes="1" />
					<result value="Not Recommended" numvotes="8" />
				</results>					
			
		<results numplayers="3">		
					<result value="Best" numvotes="1" />
					<result value="Recommended" numvotes="7" />
					<result value="Not Recommended" numvotes="4" />
				</results>					
			
		<results numplayers="4">		
					<result value="Best" numvotes="6" />
					<result value="Recommended" numvotes="6" />
					<result value="Not Recommended" numvotes="0" />
				</results>					
			
		<results numplayers="5">		
					<result value="Best" numvotes="10" />
					<result value="Recommended" numvotes="3" />
					<result value="Not Recommended" numvotes="0" />
				</results>					
			
		<results numplayers="6">		
					<result value="Best" numvotes="4" />
					<result value="Recommended" numvotes="5" />
					<result value="Not Recommended" numvotes="2" />
				</results>					
			
		<results numplayers="6+">		
					<result value="Best" numvotes="0" />
					<result value="Recommended" numvotes="0" />
					<result value="Not Recommended" numvotes="7" />
				</results>					
	</poll> 
			               				<playingtime value="120" />
						               				<minplaytime value="120" />
						               				<maxplaytime value="120" />
						               				<minage value="12" />
						      			<poll name="suggested_playerage" title="User Suggested Player Age" totalvotes="3">
			<results>		
					<result value="2" numvotes="0" />
					<result value="3" numvotes="0" />
					<result value="4" numvotes="0" />
					<result value="5" numvotes="0" />
					<result value="6" numvotes="0" />
					<result value="8" numvotes="0" />
					<result value="10" numvotes="1" />
					<result value="12" numvotes="1" />
					<result value="14" numvotes="1" />
					<result value="16" numvotes="0" />
					<result value="18" numvotes="0" />
					<result value="21 and up" numvotes="0" />
				</results>					
	</poll> 
			      			<poll name="language_dependence" title="Language Dependence" totalvotes="5">
			
		<results>		
					<result level="6" value="No necessary in-game text" numvotes="0" />
					<result level="7" value="Some necessary text - easily memorized or small crib sheet" numvotes="0" />
					<result level="8" value="Moderate in-game text - needs crib sheet or paste ups" numvotes="4" />
					<result level="9" value="Extensive use of text - massive conversion needed to be playable" numvotes="1" />
					<result level="10" value="Unplayable in another language" numvotes="0" />
				</results>					
	</poll> 
			      			 
			      				
		 			

			
		
					<link type="boardgamecategory" id="1022" value="Adventure" />
		
									
				
		 			

			
		
					<link type="boardgamecategory" id="1042" value="Expansion for Base-game" />
		
									
				
		 			

			
		
					<link type="boardgamecategory" id="1010" value="Fantasy" />
		
									
				
		 			

			
		
					<link type="boardgamecategory" id="1093" value="Novel-based" />
		
									
			

			      				
		 			

			
		
					<link type="boardgamemechanic" id="2072" value="Dice Rolling" />
		
									
				
		 			

			
		
					<link type="boardgamemechanic" id="2040" value="Hand Management" />
		
									
				
		 			

			
		
					<link type="boardgamemechanic" id="2015" value="Variable Player Powers" />
		
									
			

			      				
		 			

			
		
					<link type="boardgamefamily" id="4684" value="Lord of the Rings (Reiner Knizia's co-op game)" />
		
									
				
		 			

			
		
					<link type="boardgamefamily" id="4263" value="Tolkien Games" />
		
									
			

			      			

			      				
		 			

			
		
					<link type="boardgameexpansion" id="823" value="Lord of the Rings" inbound="true"/>
		
									
			

			      			

			      			

			      			

			      			

			      			

			      	      	      				
		 			

			
		
					<link type="boardgamedesigner" id="2" value="Reiner Knizia" />
		
									
			

			      				
		 			

			
		
					<link type="boardgameartist" id="29009" value="Bluguy" />
		
									
				
		 			

			
		
					<link type="boardgameartist" id="11884" value="John Howe" />
		
									
			

			      	      				
		 			

			
		
					<link type="boardgamepublisher" id="267" value="999 Games" />
		
									
				
		 			

			
		
					<link type="boardgamepublisher" id="253" value="Editrice Giochi" />
		
									
				
		 			

			
		
					<link type="boardgamepublisher" id="17" value="Fantasy Flight Games" />
		
									
				
		 			

			
		
					<link type="boardgamepublisher" id="51" value="Hasbro" />
		
									
				
		 			

			
		
					<link type="boardgamepublisher" id="37" value="KOSMOS" />
		
									
				
		 			

			
		
					<link type="boardgamepublisher" id="28" value="Parker Brothers" />
		
									
				
		 			

			
		
					<link type="boardgamepublisher" id="36" value="Sophisticated Games" />
		
									
				
		 			

			
		
					<link type="boardgamepublisher" id="42" value="Tilsit" />
		
									
			

			
	

	

	
	
	
   		<statistics page="1">
								<ratings >
			<usersrated value="1472" />
			<average value="6.89628" />
			<bayesaverage value="6.37617" />

			<ranks>
															<rank type="subtype" id="1" name="boardgame" friendlyname="Board Game Rank" value="Not Ranked" bayesaverage="6.37617" />
																				<rank type="family" id="5496" name="thematic" friendlyname="Thematic Rank" value="Not Ranked" bayesaverage="6.55114" />
											<rank type="family" id="5497" name="strategygames" friendlyname="Strategy Game Rank" value="Not Ranked" bayesaverage="6.47097" />
												</ranks>

			<stddev value="1.45226" />
			<median value="0" />
			<owned value="4378" />
			<trading value="187" />
			<wanting value="103" />
			<wishing value="211" />
			<numcomments value="713" />
			<numweights value="157" />
			<averageweight value="2.8217" />
			</ratings>
								</statistics>
     
	
          
</item>
<item type="boardgameexpansion" id="72661">
         <thumbnail>//cf.geekdo-images.com/images/pic149439_t.jpg</thumbnail>
      <image>//cf.geekdo-images.com/images/pic149439.jpg</image>
                                     				
				<name type="primary" sortindex="1" value="Lord of the Rings: The Black Gate" />
			
						                               				
				<name type="alternate" sortindex="5" value="Der Herr der Ringe: Das Schwarze Tor" />
			
						               													<description>A 4-Card Promo pack, distributed by Fantasy Flight Games, released at Origins 2002.&amp;#10;&amp;#10;It includes two cards which were later released with the Lord of the Rings: Sauron expansion, The One Ring &amp;amp; Watchful Peace, as well as the exclusive release, The Black Gate. The fourth card is simply &amp;quot;cover art&amp;quot; and an explanation of the other cards.&amp;#10;&amp;#10;The Black Gate card is two sided, and adds a bit more of a challenge for the Hobbits to win via Military Victory, which was a path to victory added in from the Lord of the Rings : Friends &amp;amp; Foes expansion.&amp;#10;&amp;#10;</description>
										      	               				<yearpublished value="2002" />
						               				<minplayers value="2" />
						               				<maxplayers value="6" />
						      			<poll name="suggested_numplayers" title="User Suggested Number of Players" totalvotes="0">
			
		<results numplayers="1">		
					<result value="Best" numvotes="0" />
					<result value="Recommended" numvotes="0" />
					<result value="Not Recommended" numvotes="0" />
				</results>					
			
		<results numplayers="2">		
					<result value="Best" numvotes="0" />
					<result value="Recommended" numvotes="0" />
					<result value="Not Recommended" numvotes="0" />
				</results>					
			
		<results numplayers="3">		
					<result value="Best" numvotes="0" />
					<result value="Recommended" numvotes="0" />
					<result value="Not Recommended" numvotes="0" />
				</results>					
			
		<results numplayers="4">		
					<result value="Best" numvotes="0" />
					<result value="Recommended" numvotes="0" />
					<result value="Not Recommended" numvotes="0" />
				</results>					
			
		<results numplayers="5">		
					<result value="Best" numvotes="0" />
					<result value="Recommended" numvotes="0" />
					<result value="Not Recommended" numvotes="0" />
				</results>					
			
		<results numplayers="6">		
					<result value="Best" numvotes="0" />
					<result value="Recommended" numvotes="0" />
					<result value="Not Recommended" numvotes="0" />
				</results>					
			
		<results numplayers="6+">		
					<result value="Best" numvotes="0" />
					<result value="Recommended" numvotes="0" />
					<result value="Not Recommended" numvotes="0" />
				</results>					
	</poll> 
			               				<playingtime value="60" />
						               				<minplaytime value="60" />
						               				<maxplaytime value="60" />
						               				<minage value="12" />
						      			<poll name="suggested_playerage" title="User Suggested Player Age" totalvotes="0">
	</poll> 
			      			<poll name="language_dependence" title="Language Dependence" totalvotes="1">
			
		<results>		
					<result level="1" value="No necessary in-game text" numvotes="0" />
					<result level="2" value="Some necessary text - easily memorized or small crib sheet" numvotes="1" />
					<result level="3" value="Moderate in-game text - needs crib sheet or paste ups" numvotes="0" />
					<result level="4" value="Extensive use of text - massive conversion needed to be playable" numvotes="0" />
					<result level="5" value="Unplayable in another language" numvotes="0" />
				</results>					
	</poll> 
			      			 
			      				
		 			

			
		
					<link type="boardgamecategory" id="1022" value="Adventure" />
		
									
				
		 			

			
		
					<link type="boardgamecategory" id="1042" value="Expansion for Base-game" />
		
									
				
		 			

			
		
					<link type="boardgamecategory" id="1010" value="Fantasy" />
		
									
				
		 			

			
		
					<link type="boardgamecategory" id="1093" value="Novel-based" />
		
									
				
		 			

			
		
					<link type="boardgamecategory" id="1120" value="Print &amp; Play" />
		
									
			

			      				
		 			

			
		
					<link type="boardgamemechanic" id="2023" value="Co-operative Play" />
		
									
				
		 			

			
		
					<link type="boardgamemechanic" id="2072" value="Dice Rolling" />
		
									
				
		 			

			
		
					<link type="boardgamemechanic" id="2040" value="Hand Management" />
		
									
				
		 			

			
		
					<link type="boardgamemechanic" id="2011" value="Modular Board" />
		
									
				
		 			

			
		
					<link type="boardgamemechanic" id="2015" value="Variable Player Powers" />
		
									
			

			      				
		 			

			
		
					<link type="boardgamefamily" id="4256" value="Kosmos Literature Series" />
		
									
				
		 			

			
		
					<link type="boardgamefamily" id="4684" value="Lord of the Rings (Reiner Knizia's co-op game)" />
		
									
				
		 			

			
		
					<link type="boardgamefamily" id="4263" value="Tolkien Games" />
		
									
			

			      			

			      				
		 			

			
		
					<link type="boardgameexpansion" id="823" value="Lord of the Rings" inbound="true"/>
		
									
				
		 			

			
		
					<link type="boardgameexpansion" id="2449" value="Lord of the Rings: Friends &amp; Foes" inbound="true"/>
		
									
			

			      			

			      			

			      			

			      			

			      			

			      	      	      				
		 			

			
		
					<link type="boardgamedesigner" id="2" value="Reiner Knizia" />
		
									
			

			      				
		 			

			
		
					<link type="boardgameartist" id="29009" value="Bluguy" />
		
									
				
		 			

			
		
					<link type="boardgameartist" id="11884" value="John Howe" />
		
									
			

			      	      				
		 			

			
		
					<link type="boardgamepublisher" id="17" value="Fantasy Flight Games" />
		
									
				
		 			

			
		
					<link type="boardgamepublisher" id="37" value="KOSMOS" />
		
									
			

			
	

	

	
	
	
   		<statistics page="1">
								<ratings >
			<usersrated value="32" />
			<average value="7.39062" />
			<bayesaverage value="5.57442" />

			<ranks>
															<rank type="subtype" id="1" name="boardgame" friendlyname="Board Game Rank" value="Not Ranked" bayesaverage="5.57442" />
												</ranks>

			<stddev value="0.9661" />
			<median value="0" />
			<owned value="141" />
			<trading value="9" />
			<wanting value="51" />
			<wishing value="84" />
			<numcomments value="34" />
			<numweights value="5" />
			<averageweight value="2.4" />
			</ratings>
								</statistics>
     
	
          
</item>
</items>